tagrenamer/__init__.py
tagrenamer/cli.py
tagrenamer/app/__init__.py
tagrenamer/app/collection.py
tagrenamer/app/output.py
tagrenamer/app/safestring.py
tagrenamer/app/settings.py
tagrenamer/fs/__init__.py
tagrenamer/fs/directory.py
tagrenamer/fs/file.py
tagrenamer/fs/musicfile.py
tagrenamer/fs/node.py
tagrenamer-0.0.3.dist-info/LICENSE
tagrenamer-0.0.3.dist-info/METADATA
tagrenamer-0.0.3.dist-info/WHEEL
tagrenamer-0.0.3.dist-info/entry_points.txt
tagrenamer-0.0.3.dist-info/top_level.txt
tagrenamer-0.0.3.dist-info/RECORD
