Metadata-Version: 2.1
Name: tagrenamer
Version: 0.0.3
Summary: Mass music collection renamer.
Home-page: https://github.com/nielsvm/tagrenamer
Author: Niels van Mourik
Author-email: niels@nielsvm.org
License: GNU General Public License v3
Keywords: tagrenamer
Classifier: Development Status :: 2 - Pre-Alpha
Classifier: Intended Audience :: End Users/Desktop
Classifier: License :: OSI Approved :: GNU General Public License v3 (GPLv3)
Classifier: Natural Language :: English
Classifier: Programming Language :: Python :: 3
Classifier: Programming Language :: Python :: 3.6
Classifier: Programming Language :: Python :: 3.7
Classifier: Programming Language :: Python :: 3.8
Requires-Python: >=3.6
License-File: LICENSE
Requires-Dist: pytaglib
Requires-Dist: transliterate
